pymarine/__init__.py
pymarine/utils/__init__.py
pymarine/utils/coordinate_transformations.py
pymarine/utils/date_time.py
pymarine/utils/file_and_directory.py
pymarine/utils/geographic.py
pymarine/utils/misc.py
pymarine/utils/numerical.py
pymarine/utils/plotting.py
pymarine/waves/wave_fields.py
pymarine/waves/wave_spectra.py
pymarine-0.1.5.dist-info/LICENSE.txt
pymarine-0.1.5.dist-info/METADATA
pymarine-0.1.5.dist-info/WHEEL
pymarine-0.1.5.dist-info/top_level.txt
pymarine-0.1.5.dist-info/RECORD
