Metadata-Version: 2.1
Name: pymarine
Version: 0.1.5
Summary: A collection of functions and classes for marine sea state modelling
Home-page: https://github.com/eelcovv/pymarine
Author: Eelco van Vliet
Author-email: eelcovv@gmail.nl
License: MIT
Project-URL: Documentation, https://pymarine.readthedocs.io/en/latest/
Platform: any
Classifier: Development Status :: 4 - Beta
Classifier: Programming Language :: Python
License-File: LICENSE.txt
Requires-Dist: python-dateutil
Requires-Dist: fastkml
Requires-Dist: numpy
Requires-Dist: pandas
Requires-Dist: pint
Requires-Dist: pyyaml
Requires-Dist: lxml
Requires-Dist: colorcet
Requires-Dist: latloncalc
Requires-Dist: h5py
Requires-Dist: netCDF4
Requires-Dist: scipy
Requires-Dist: statsmodels
Requires-Dist: matplotlib
Requires-Dist: seaborn
Requires-Dist: importlib-metadata ; python_version < "3.8"
Provides-Extra: dev
Requires-Dist: pre-commit ; extra == 'dev'
Requires-Dist: black ; extra == 'dev'
Requires-Dist: tox ; extra == 'dev'
Provides-Extra: testing
Requires-Dist: setuptools ; extra == 'testing'
Requires-Dist: pytest ; extra == 'testing'
Requires-Dist: pytest-cov ; extra == 'testing'
